README.md
deprecated_decorator/__init__.py
pylint_deprecated_decorator-0.2.4.dist-info/WHEEL
pylint_deprecated_decorator-0.2.4.dist-info/METADATA
pylint_deprecated_decorator-0.2.4.dist-info/RECORD
